<?xml version="1.0" encoding="UTF-8"?>
<beans xmlns="http://www.springframework.org/schema/beans"
	xmlns:mvc="http://www.springframework.org/schema/mvc"
    xmlns:xsi="http://www.w3.org/2001/XMLSchema-instance"
    xsi:schemaLocation="http://www.springframework.org/schema/beans
        https://www.springframework.org/schema/beans/spring-beans.xsd
        http://www.springframework.org/schema/mvc
        https://www.springframework.org/schema/mvc/spring-mvc.xsd">

	<!-- /index url요청이 오면 class를 객체화하여 호출 -->
    <bean id="/index" class="com.newlecture.web.controller.indexController"/> 
    <bean id="/notice/list" class="com.newlecture.web.controller.notice.ListController"/>  
    <bean id="/notice/detail" class="com.newlecture.web.controller.notice.DetailController"/>  
    
    
	<!-- tilesViewResolver설정 -->
	<bean class="org.springframework.web.servlet.view.UrlBasedViewResolver">
	    <property name="viewClass" 
	    		  value="org.springframework.web.servlet.view.tiles3.TilesView" />
	    <property name="order" value="1" /> <!-- 순서1 -->
	</bean>
	
	<bean
	    class="org.springframework.web.servlet.view.tiles3.TilesConfigurer">
	    <property name="definitions" value="/WEB-INF/tiles.xml" />
	</bean>
  

	<!-- view까지 경로 ?-->
	<bean class="org.springframework.web.servlet.view.InternalResourceViewResolver">
		<property name="prefix" value="/WEB-INF/view/"></property>
		<property name="suffix" value=".jsp"></property>
		<property name="order" value="2" /> <!-- 순서2 -->
		
	</bean>
	
	<mvc:resources location="/static/" mapping="/**"></mvc:resources>
</beans>